compdfkit/__init__.py
compdfkit/client.py
compdfkit/constant.py
compdfkit/enums.py
compdfkit/exception.py
compdfkit/param.py
compdfkit/utils.py
compdfkit/pojo/__init__.py
compdfkit/pojo/compdfkit.py
test/__init__.py
test/test_utils_pytest.py
compdfkit_api_python-1.3.3.dist-info/LICENSE.txt
compdfkit_api_python-1.3.3.dist-info/METADATA
compdfkit_api_python-1.3.3.dist-info/WHEEL
compdfkit_api_python-1.3.3.dist-info/top_level.txt
compdfkit_api_python-1.3.3.dist-info/RECORD
