Metadata-Version: 2.1
Name: compdfkit-api-python
Version: 1.3.3
Summary: Python SDK for compdfkit API
Home-page: https://api.compdf.com/api-reference/overview
Author: PDF Technologies, Inc.
Author-email: support@compdf.com
License: MIT License
Requires-Python: >=3.8
License-File: LICENSE.txt
Requires-Dist: requests
Requires-Dist: requests-toolbelt
